{
	"params": {

	},
	"slides": [
		{
			"equilibration_steps": {"Int": 10},
			"measurement_freq": {"Int": 2},
			"partition_size": {"Int": 1},
			"system_size": {"Int": 2},
			"timesteps": {"Int": 10},
			"beta": {"Float": 0.500000},
			"filling_fraction": {"Float": 0.500000},
			"p1": {"Float": 0.200000},
			"p2": {"Float": 0.300000},
			"entropy": {"Data": [[-12.106869, 0.000000, 1.000000]]}
		},
		{
			"equilibration_steps": {"Int": 10},
			"measurement_freq": {"Int": 2},
			"partition_size": {"Int": 1},
			"system_size": {"Int": 4},
			"timesteps": {"Int": 10},
			"beta": {"Float": 0.500000},
			"filling_fraction": {"Float": 0.500000},
			"p1": {"Float": 0.200000},
			"p2": {"Float": 0.300000},
			"entropy": {"Data": [[-25.846436, 0.000000, 1.000000]]}
		}
	]
}
